islatu/__init__.py
islatu/background.py
islatu/corrections.py
islatu/cropping.py
islatu/data.py
islatu/debug.py
islatu/image.py
islatu/io.py
islatu/metadata.py
islatu/refl_profile.py
islatu/region.py
islatu/runner.py
islatu/scan.py
islatu/stitching.py
islatu-1.1.0.dist-info/licenses/LICENSE
islatu-1.1.0.dist-info/METADATA
islatu-1.1.0.dist-info/WHEEL
islatu-1.1.0.dist-info/top_level.txt
islatu-1.1.0.dist-info/RECORD
