Metadata-Version: 2.4
Name: islatu
Version: 1.1.0
Summary: A package for the reduction of reflectometry data.
Author: Philip Mousley
Author-email: philip.mousley@diamond.ac.uk
License: MIT
Classifier: Development Status :: 5 - Production/Stable
Classifier: Intended Audience :: Science/Research
Classifier: License :: OSI Approved :: MIT License
Classifier: Natural Language :: English
Classifier: Operating System :: OS Independent
Classifier: Programming Language :: Python
Classifier: Programming Language :: Python :: 3.5
Classifier: Programming Language :: Python :: 3.6
Classifier: Programming Language :: Python :: 3.7
Classifier: Programming Language :: Python :: 3.8
Classifier: Programming Language :: Python :: 3.9
Classifier: Programming Language :: Python :: 3.10
Classifier: Programming Language :: Python :: Implementation :: CPython
Classifier: Topic :: Scientific/Engineering
Classifier: Topic :: Scientific/Engineering :: Chemistry
Classifier: Topic :: Scientific/Engineering :: Physics
License-File: LICENSE
Requires-Dist: wheel
Requires-Dist: numpy
Requires-Dist: scipy
Requires-Dist: coverage
Requires-Dist: pandas
Requires-Dist: pyyaml
Requires-Dist: nexusformat
Requires-Dist: pytest
Requires-Dist: pytest-lazy-fixture
Requires-Dist: nbsphinx
Requires-Dist: jupyter-sphinx
Requires-Dist: jupyterlab
Requires-Dist: ipywidgets
Requires-Dist: pytest-cov
Dynamic: author
Dynamic: author-email
Dynamic: classifier
Dynamic: description
Dynamic: license
Dynamic: license-file
Dynamic: requires-dist
Dynamic: summary
